{"id":"9423bb27-1ac2-4e85-9fb9-f3e82679f3cb","timestamp":1743957631499,"matcher":{"static":{"/__nuxt_content/content/sql_dump":{"prerender":true},"/__nuxt_content/news/sql_dump":{"prerender":true},"/__nuxt_content/archive/sql_dump":{"prerender":true}},"wildcard":{},"dynamic":{}},"prerendered":["/","/about","/news/news0005","/news/news0001","/archive","/news","/news/news0002","/news/news0003","/news/news0004","/archive/archive0005","/archive/archive0003","/archive/archive0002","/archive/archive0006","/archive/archive0004","/archive/archive0001"]}